AUTHORS
CHANGES.md
LICENSE
MANIFEST.in
README.rst
setup.py
docs/cassandra.rst
maelstrom/__init__.py
maelstrom/base.py
maelstrom/cass_conn.py
maelstrom/data.py
maelstrom/db_utils.py
maelstrom/exceptions.py
maelstrom/lookup.py
maelstrom/row.py
maelstrom/search.py
maelstrom/tests/__init__.py
maelstrom/tests/account.py
maelstrom/tests/test.py
maelstrom/tests/test_connect.py
maelstrom/tests/test_db_utils.py
maelstrom/tests/test_search.py
maelstrom_py.egg-info/PKG-INFO
maelstrom_py.egg-info/SOURCES.txt
maelstrom_py.egg-info/dependency_links.txt
maelstrom_py.egg-info/requires.txt
maelstrom_py.egg-info/top_level.txt