Metadata-Version: 1.0
Name: maelstrom-py
Version: 0.1.4
Summary: A powerful, model based Cassandra wrapper for Python.
Home-page: https://github.com/gradfly/maelstrom
Author: Matt Morse, Joe Peacock
Author-email: mmorse1217@gmail.com, joeapeacock@gmail.com
License: LICENSE
Platform: UNKNOWN
